MEDS_extract/__init__.py
MEDS_extract/parsing.py
MEDS_extract/configs/__init__.py
MEDS_extract/configs/_extract.yaml
MEDS_extract/convert_to_MEDS_events/__init__.py
MEDS_extract/convert_to_MEDS_events/config.yaml
MEDS_extract/convert_to_MEDS_events/convert_to_MEDS_events.py
MEDS_extract/convert_to_subject_sharded/__init__.py
MEDS_extract/convert_to_subject_sharded/convert_to_subject_sharded.py
MEDS_extract/extract_code_metadata/__init__.py
MEDS_extract/extract_code_metadata/config.yaml
MEDS_extract/extract_code_metadata/extract_code_metadata.py
MEDS_extract/extract_code_metadata/utils.py
MEDS_extract/finalize_MEDS_data/__init__.py
MEDS_extract/finalize_MEDS_data/finalize_MEDS_data.py
MEDS_extract/finalize_MEDS_metadata/__init__.py
MEDS_extract/finalize_MEDS_metadata/finalize_MEDS_metadata.py
MEDS_extract/merge_to_MEDS_cohort/__init__.py
MEDS_extract/merge_to_MEDS_cohort/config.yaml
MEDS_extract/merge_to_MEDS_cohort/merge_to_MEDS_cohort.py
MEDS_extract/shard_events/__init__.py
MEDS_extract/shard_events/config.yaml
MEDS_extract/shard_events/shard_events.py
MEDS_extract/split_and_shard_subjects/__init__.py
MEDS_extract/split_and_shard_subjects/config.yaml
MEDS_extract/split_and_shard_subjects/split_and_shard_subjects.py
meds_extract-0.5.0.dist-info/licenses/LICENSE
meds_extract-0.5.0.dist-info/METADATA
meds_extract-0.5.0.dist-info/WHEEL
meds_extract-0.5.0.dist-info/entry_points.txt
meds_extract-0.5.0.dist-info/top_level.txt
meds_extract-0.5.0.dist-info/RECORD
