Metadata-Version: 2.4
Name: MEDS_extract
Version: 0.5.0
Summary: MEDS ETL building support leveraging MEDS-Transforms.
Author-email: Matthew McDermott <mattmcdermott8@gmail.com>
Project-URL: Homepage, https://github.com/mmcdermott/MEDS_extract
Project-URL: Issues, https://github.com/mmcdermott/MEDS_extract/issues
Classifier: Programming Language :: Python :: 3
Classifier: License :: OSI Approved :: MIT License
Classifier: Operating System :: OS Independent
Requires-Python: >=3.11
License-File: LICENSE
Requires-Dist: polars>=1.26
Requires-Dist: pyarrow
Requires-Dist: hydra-core
Requires-Dist: numpy
Requires-Dist: meds~=0.4.0
Requires-Dist: MEDS-transforms~=0.6.0
Requires-Dist: universal_pathlib
Provides-Extra: dev
Requires-Dist: pre-commit<4; extra == "dev"
Requires-Dist: ruff; extra == "dev"
Provides-Extra: tests
Requires-Dist: pytest; extra == "tests"
Requires-Dist: pytest-cov; extra == "tests"
Requires-Dist: pytest-notebook; extra == "tests"
Requires-Dist: hydra-joblib-launcher; extra == "tests"
Requires-Dist: meds_testing_helpers>=0.2.1; extra == "tests"
Provides-Extra: example
Requires-Dist: jupyter; extra == "example"
Provides-Extra: local-parallelism
Requires-Dist: hydra-joblib-launcher; extra == "local-parallelism"
Provides-Extra: slurm-parallelism
Requires-Dist: hydra-submitit-launcher; extra == "slurm-parallelism"
Provides-Extra: docs
Requires-Dist: mkdocs==1.6.1; extra == "docs"
Requires-Dist: mkdocs-material==9.6.7; extra == "docs"
Requires-Dist: mkdocstrings[python,shell]==0.28.2; extra == "docs"
Requires-Dist: mkdocs-gen-files==0.5.0; extra == "docs"
Requires-Dist: mkdocs-literate-nav==0.6.1; extra == "docs"
Requires-Dist: mkdocs-section-index==0.3.9; extra == "docs"
Requires-Dist: mkdocs-git-authors-plugin==0.9.2; extra == "docs"
Requires-Dist: mkdocs-git-revision-date-localized-plugin==1.3.0; extra == "docs"
Dynamic: license-file
